Metadata-Version: 2.1
Name: djangohmacv3
Version: 1.3.4
Summary: Provides easy integration of the HMAC signatures for your REST Django Applications.
Home-page: https://github.com/EralpBay/djangohmac
Author: SOON_
Author-email: dorks@thisissoon.com
License: Public Domain
Keywords: Django,HMAC,REST,Views,middleware
Platform: UNKNOWN
Classifier: Framework :: Django
Classifier: Environment :: Web Environment
Classifier: Intended Audience :: Developers
Classifier: License :: OSI Approved :: MIT License
Classifier: Development Status :: 5 - Production/Stable
Classifier: Operating System :: OS Independent
Classifier: Programming Language :: Python
Classifier: Programming Language :: Python :: 2.7
Classifier: Programming Language :: Python :: 3
Classifier: Programming Language :: Python :: 3.3
Classifier: Programming Language :: Python :: 3.4
Classifier: Topic :: Software Development
Classifier: Topic :: Software Development :: Libraries :: Python Modules
Classifier: Topic :: Internet :: WWW/HTTP :: Dynamic Content
Classifier: License :: Public Domain
License-File: LICENSE
